e4ting/__init__.py
e4ting/acl/__init__.py
e4ting/acl/base.py
e4ting/acl/models/admin.model
e4ting/acl/models/admin.policy
e4ting/api/__init__.py
e4ting/api/__main__.py
e4ting/api/cas.py
e4ting/api/frp.py
e4ting/api/spug.py
e4ting/cache/__init__.py
e4ting/cache/cache.py
e4ting/cluster/__init__.py
e4ting/cluster/callee.py
e4ting/cluster/cloud.py
e4ting/cluster/control.py
e4ting/cluster/fuse.py
e4ting/db/__init__.py
e4ting/db/kaf.py
e4ting/db/pymongos.py
e4ting/db/utilredis.py
e4ting/etc/__init__.py
e4ting/etc/utilyaml.py
e4ting/log/__init__.py
e4ting/log/all_exception.py
e4ting/log/otherhandle.py
e4ting/log/syslogs.py
e4ting/net/__init__.py
e4ting/net/iface.py
e4ting/server/__init__.py
e4ting/server/call.py
e4ting/server/e4ting_pb2.py
e4ting/server/e4ting_pb2_grpc.py
e4ting/server/restful.py
e4ting/server/rpc.py
e4ting/server/util.py
e4ting/task/__init__.py
e4ting/task/base.py
e4ting/task/celeryproxy.py
e4ting/task/engine.py
e4ting/task/master.py
e4ting/task/worker.py
e4ting/util/__init__.py
e4ting/util/common.py
e4ting/util/feichang.py
e4ting/util/fuser.py
e4ting/util/hardware.py
e4ting/util/hidden.py
e4ting/util/remote_fuser.py
e4ting/util/rsa.py
e4ting/util/url2img.py
e4ting/util/util.py
e4ting-1.1.15127.dist-info/METADATA
e4ting-1.1.15127.dist-info/WHEEL
e4ting-1.1.15127.dist-info/top_level.txt
e4ting-1.1.15127.dist-info/RECORD
