Metadata-Version: 2.1
Name: e4ting
Version: 1.1.15127
Summary: 陈狍子的私人库
Author: e4ting
Author-email: e4tingcom@gmail.com
Classifier: License :: OSI Approved :: MIT License
Classifier: Programming Language :: Python
Classifier: Intended Audience :: Developers
Classifier: Operating System :: OS Independent
